setup.cfg
setup.py
oz/__init__.py
oz/oz_core_api.py
oz_python_client.egg-info/PKG-INFO
oz_python_client.egg-info/SOURCES.txt
oz_python_client.egg-info/dependency_links.txt
oz_python_client.egg-info/requires.txt
oz_python_client.egg-info/top_level.txt