Metadata-Version: 1.0
Name: oz-python-client
Version: 0.4.0
Summary: A python client to the OZ API
Home-page: https://github.com/ozinc/oz-python-client
Author: Kari Tristan Helgason
Author-email: kari@oz.com
License: UNKNOWN
Keywords: oz,api-client,example
Platform: UNKNOWN
